postnlecommerceapis/__init__.py
postnlecommerceapis/api_helper.py
postnlecommerceapis/configuration.py
postnlecommerceapis/postnlecommerceapis_client.py
postnlecommerceapis/controllers/__init__.py
postnlecommerceapis/controllers/barcode_controller.py
postnlecommerceapis/controllers/base_controller.py
postnlecommerceapis/controllers/checkout_controller.py
postnlecommerceapis/controllers/confirming_controller.py
postnlecommerceapis/controllers/deliverydate_controller.py
postnlecommerceapis/controllers/labelling_controller.py
postnlecommerceapis/controllers/locations_controller.py
postnlecommerceapis/controllers/postalcode_check_controller.py
postnlecommerceapis/controllers/timeframes_controller.py
postnlecommerceapis/controllers/track_trace_controller.py
postnlecommerceapis/exceptions/__init__.py
postnlecommerceapis/exceptions/api_exception.py
postnlecommerceapis/exceptions/barcode_method_not_allowed_exception.py
postnlecommerceapis/exceptions/barcode_response_error_exception.py
postnlecommerceapis/exceptions/barcode_response_invalid_exception.py
postnlecommerceapis/exceptions/barcode_too_many_request_exception.py
postnlecommerceapis/exceptions/checkout_postal_codecheck_method_not_allowed_exception.py
postnlecommerceapis/exceptions/checkout_postal_codecheck_too_many_request_exception.py
postnlecommerceapis/exceptions/checkout_postal_codecheck_unauthorized_exception.py
postnlecommerceapis/exceptions/checkout_response_error_exception.py
postnlecommerceapis/exceptions/checkout_response_invalid_exception.py
postnlecommerceapis/exceptions/confirming_method_not_allowed_exception.py
postnlecommerceapis/exceptions/confirming_response_error_1_exception.py
postnlecommerceapis/exceptions/confirming_response_error_exception.py
postnlecommerceapis/exceptions/confirming_too_many_request_exception.py
postnlecommerceapis/exceptions/confirming_unauthorized_exception.py
postnlecommerceapis/exceptions/cpc_response_error_exception.py
sdksio_postnl_ecommerce_apis_sdk-1.0.0.dist-info/LICENSE
sdksio_postnl_ecommerce_apis_sdk-1.0.0.dist-info/METADATA
sdksio_postnl_ecommerce_apis_sdk-1.0.0.dist-info/WHEEL
sdksio_postnl_ecommerce_apis_sdk-1.0.0.dist-info/top_level.txt
sdksio_postnl_ecommerce_apis_sdk-1.0.0.dist-info/RECORD
